setup.cfg
setup.py
conf/__init__.py
conf/mime_type.py
jss/__init__.py
jss/bucket.py
jss/commonconstants.py
jss/connection.py
jss/exception.py
jss/key.py
jss/util.py
jss_python.egg-info/PKG-INFO
jss_python.egg-info/SOURCES.txt
jss_python.egg-info/dependency_links.txt
jss_python.egg-info/top_level.txt