Metadata-Version: 1.0
Name: jss-python
Version: 1.0.1
Summary: API module for JSS
Home-page: http://www.jd.com
Author: jd
Author-email: jss@jd.com
License: LGPL
Platform: UNKNOWN
